html_to_json_blocks/__init__.py
html_to_json_blocks/converters/__init__.py
html_to_json_blocks/converters/base_converter.py
html_to_json_blocks/converters/default_converter.py
html_to_json_blocks/core.py
html_to_json_blocks/transformers/__init__.py
html_to_json_blocks/transformers/default_image_transformer.py
html_to_json_blocks/transformers/image_transformer.py
html_to_json_blocks/utils.py
html_to_json_blocks-0.1.0.dist-info/LICENSE
html_to_json_blocks-0.1.0.dist-info/METADATA
html_to_json_blocks-0.1.0.dist-info/WHEEL
html_to_json_blocks-0.1.0.dist-info/RECORD
