Metadata-Version: 2.1
Name: html-to-json-blocks
Version: 0.1.0
Summary: Una herramienta para convertir bloques de HTML a JSON
Home-page: https://github.com/nivektakedown/html-to-json-blocks
License: MIT
Author: Tu Nombre
Author-email: kevinframosl@gmail.com
Requires-Python: >=3.12,<4.0
Classifier: License :: OSI Approved :: MIT License
Classifier: Programming Language :: Python :: 3
Classifier: Programming Language :: Python :: 3.12
Classifier: Programming Language :: Python :: 3.13
Requires-Dist: coverage (>=7.6.4,<8.0.0)
Requires-Dist: pytest (>=6.2.5,<7.0.0)
Project-URL: Repository, https://github.com/nivektakedown/html-to-json-blocks
